metadist/__init__.py
metadist/config.py
metadist/version.py
metadist/autoflow/__init__.py
metadist/autoflow/solver.py
metadist/jax/__init__.py
metadist/jax/api.py
metadist/jax/bridge.py
metadist/jax/device_mesh.py
metadist/jax/sharding_interpreter.py
metadist/jax/utils.py
metadist/metashard/__init__.py
metadist/metashard/annotation.py
metadist/metashard/combination.py
metadist/metashard/halo.py
metadist/metashard/metair.py
metadist/metashard/metaop.py
metadist/metashard/view_propagation.py
metadist/platform/__init__.py
metadist/platform/jax.py
metadist/platform/torch.py
metadist/platform/tvm.py
metadist/torch/__init__.py
metadist/torch/api.py
metadist/torch/bridge.py
metadist/torch/device_mesh.py
metadist/torch/mem_anaylize.py
metadist/torch/preset_propagation.py
metadist/torch/sharding_interpreter.py
metadist/torch/spmd_prop_rule.py
metadist/torch/utils.py
metadist/torch/experimental/__init__.py
metadist/torch/experimental/api.py
metadist/torch/experimental/compiler.py
metadist/torch/experimental/decomp_utils.py
metadist/torch/experimental/init_helper.py
metadist/torch/passes/__init__.py
metadist/torch/passes/eliminate_detach.py
metadist/torch/passes/fix_bias.py
metadist/torch/passes/fix_embedding.py
metadist/torch/passes/fix_meta_device.py
metadist/torch/passes/sharding.py
metadist/utils/__init__.py
metadist/utils/testing.py
metadist/utils/timer.py
metadist-0.1.1.dist-info/LICENSE
metadist-0.1.1.dist-info/METADATA
metadist-0.1.1.dist-info/NOTICE
metadist-0.1.1.dist-info/WHEEL
metadist-0.1.1.dist-info/top_level.txt
metadist-0.1.1.dist-info/RECORD
