Metadata-Version: 2.1
Name: metadist
Version: 0.1.1
Summary: Efficient Automatic Training System for Super-Large Models
Home-page: https://github.com/alibaba/easydist
Author: Shenggan Cheng
Author-email: shenggan.c@u.nus.edu
License-File: LICENSE
License-File: NOTICE
Requires-Dist: pyyaml
Requires-Dist: rich
Requires-Dist: mip (>=1.13)
Provides-Extra: jax
Requires-Dist: jax[cuda11_pip] ; extra == 'jax'
Requires-Dist: flax ; extra == 'jax'
Provides-Extra: torch
Requires-Dist: torch ; extra == 'torch'
Requires-Dist: torchvision ; extra == 'torch'
